is_msgs/__init__.py
is_msgs/camera.proto
is_msgs/camera_pb2.py
is_msgs/common.proto
is_msgs/common_pb2.py
is_msgs/image.proto
is_msgs/image_pb2.py
is_msgs/power.proto
is_msgs/power_pb2.py
is_msgs/robot.proto
is_msgs/robot_pb2.py
is_msgs/tests.proto
is_msgs/tests_pb2.py
is_msgs/validate.proto
is_msgs/validate_pb2.py
is_msgs/utils/__init__.py
is_msgs/utils/build.py
is_msgs-1.1.18.dist-info/METADATA
is_msgs-1.1.18.dist-info/WHEEL
is_msgs-1.1.18.dist-info/top_level.txt
is_msgs-1.1.18.dist-info/RECORD
