Metadata-Version: 2.1
Name: is-msgs
Version: 1.1.18
Summary: Package with standard IS messages
Home-page: http://github.com/labvisio/is-msgs
Author: labvisio
Author-email: labvisio.ufes@gmail.com
License: MIT
Classifier: Intended Audience :: Developers
Classifier: Programming Language :: Python :: 3
Classifier: Programming Language :: Python :: 3.7
Classifier: Programming Language :: Python :: 3.8
Classifier: Programming Language :: Python :: 3.9
Classifier: Programming Language :: Python :: 3.10
Classifier: Programming Language :: Python :: 3 :: Only
